runloop_api_client/__init__.py
runloop_api_client/_base_client.py
runloop_api_client/_client.py
runloop_api_client/_compat.py
runloop_api_client/_constants.py
runloop_api_client/_exceptions.py
runloop_api_client/_files.py
runloop_api_client/_models.py
runloop_api_client/_qs.py
runloop_api_client/_resource.py
runloop_api_client/_response.py
runloop_api_client/_streaming.py
runloop_api_client/_types.py
runloop_api_client/_version.py
runloop_api_client/pagination.py
runloop_api_client/py.typed
runloop_api_client/_utils/__init__.py
runloop_api_client/_utils/_compat.py
runloop_api_client/_utils/_datetime_parse.py
runloop_api_client/_utils/_json.py
runloop_api_client/_utils/_logs.py
runloop_api_client/_utils/_proxy.py
runloop_api_client/_utils/_reflection.py
runloop_api_client/_utils/_resources_proxy.py
runloop_api_client/_utils/_streams.py
runloop_api_client/_utils/_sync.py
runloop_api_client/_utils/_transform.py
runloop_api_client/_utils/_typing.py
runloop_api_client/_utils/_utils.py
runloop_api_client/_utils/_validation.py
runloop_api_client/lib/.keep
runloop_api_client/lib/__init__.py
runloop_api_client/lib/_ignore.py
runloop_api_client/lib/context_loader.py
runloop_api_client/lib/polling.py
runloop_api_client/lib/polling_async.py
runloop_api_client/resources/__init__.py
runloop_api_client/resources/agents.py
runloop_api_client/resources/benchmark_jobs.py
runloop_api_client/resources/benchmark_runs.py
runloop_api_client/resources/benchmarks.py
runloop_api_client/resources/blueprints.py
runloop_api_client/resources/gateway_configs.py
runloop_api_client/resources/network_policies.py
runloop_api_client/resources/objects.py
runloop_api_client/resources/repositories.py
runloop_api_client/resources/secrets.py
runloop_api_client/resources/devboxes/__init__.py
runloop_api_client/resources/devboxes/browsers.py
runloop_api_client/resources/devboxes/computers.py
runloop_api_client/resources/devboxes/devboxes.py
runloop_api_client/resources/devboxes/disk_snapshots.py
runloop_api_client-1.5.1.dist-info/METADATA
runloop_api_client-1.5.1.dist-info/WHEEL
runloop_api_client-1.5.1.dist-info/licenses/LICENSE
runloop_api_client-1.5.1.dist-info/RECORD
