Metadata-Version: 2.3
Name: runloop_api_client
Version: 1.5.1
Summary: The official Python library for the runloop API
Project-URL: Homepage, https://github.com/runloopai/api-client-python
Project-URL: Repository, https://github.com/runloopai/api-client-python
Project-URL: Documentation, https://runloopai.github.io/api-client-python/
Author-email: Runloop <support@runloop.ai>
License: MIT
Classifier: Intended Audience :: Developers
Classifier: License :: OSI Approved :: MIT License
Classifier: Operating System :: MacOS
Classifier: Operating System :: Microsoft :: Windows
Classifier: Operating System :: OS Independent
Classifier: Operating System :: POSIX
Classifier: Operating System :: POSIX :: Linux
Classifier: Programming Language :: Python :: 3.9
Classifier: Programming Language :: Python :: 3.10
Classifier: Programming Language :: Python :: 3.11
Classifier: Programming Language :: Python :: 3.12
Classifier: Programming Language :: Python :: 3.13
Classifier: Programming Language :: Python :: 3.14
Classifier: Topic :: Software Development :: Libraries :: Python Modules
Classifier: Typing :: Typed
Requires-Python: >=3.9
Requires-Dist: anyio<5,>=3.5.0
Requires-Dist: distro<2,>=1.7.0
Requires-Dist: httpx<1,>=0.23.0
Requires-Dist: pydantic<3,>=2.0
Requires-Dist: sniffio
Requires-Dist: typing-extensions<5,>=4.10
Requires-Dist: uuid-utils>=0.11.0
Provides-Extra: aiohttp
Requires-Dist: aiohttp; extra == 'aiohttp'
Requires-Dist: httpx-aiohttp>=0.1.9; extra == 'aiohttp'
